[
  {
    "title": "超簡単！組み立て式キャッチコピーの考え方",
    "lead": "<p>小説を投稿するにあたって、キャッチコピーの設定を求めるサイトが増えてきました。<br/>「カクヨム」に「ノベルアップ＋」……身に覚えのある投稿者もいるのではないでしょうか？</p><p>しかし、いざキャッチコピーを考えようにも、ぴったりなものが思い付かない。<br/>これで本当に読んでもらえるのか不安</p><p>そんな悩みを持つ方も多いはず。</p><p>そこで今回の記事では、キャッチコピーの考え方について紹介していこうと思います。</p>",
    "created": 1647399600,
    "writer": "miura",
    "tags": [
      "書き方",
      "初心者向け"
    ],
    "related": [
      "20220313",
      "20220314",
      "20220315"
    ],
    "slug": "20220316"
  },
  {
    "title": "小説の基本！人称視点とは何か？",
    "lead": "<p>小説を読んでいる時、書き方が大きく二つに分かれていることに気づかないでしょうか。<br />私が、俺が、で進んでいく「一人称」視点。<br />さんが、Bさんが、で進んでいく「三人称」視点。<br />小説を書こうとしたとき、まずぶつかる壁がどちらの視点で書こうか、です。</p><p>今回の記事では、人称視点とは何か、またぞれぞれの特徴について解説します。</p><p>自分にあった人称視点を見つける参考になれば嬉しいです。</p>",
    "created": 1647313200,
    "writer": "hano",
    "tags": [
      "書き方",
      "初心者向け"
    ],
    "related": [
      "20220313",
      "20220314",
      "20220316"
    ],
    "slug": "20220315"
  },
  {
    "title": "ボキャブラリーの広げ方",
    "lead": "<p>あなたは小説を書くときに以下のことで悩んだことはありませんか？</p><ul><li>表現がわからない</li><li>さっきもこの言葉使ったな</li></ul><p>僕も小説を書いている中で悩むことがあります。今回の記事ではボキャブラリーの増やし方を紹介します。ボキャブラリーの数が増えると文章がくどくなくなったり、作品の質を上げることができます。<br />表現の仕方などのご参考になれば幸いです。</p>",
    "created": 1647226800,
    "writer": "sumire",
    "tags": [
      "書き方",
      "初心者向け"
    ],
    "related": [
      "20220313",
      "20220315",
      "20220316"
    ],
    "slug": "20220314"
  },
  {
    "title": "初心者向け！自作小説のキャラクターの名前の付け方",
    "lead": "<p>小説のアイデアを思いついたはいいが、登場人物・キャラクターの名前が思いつかず、執筆の手が止まってしまった経験はないでしょうか。</p><ul><li>どういう名前をつければいいかわからない</li><li>キャラクターを増やしすぎて名前が思いつかない</li><li>他の物書きさんはどうやって名前を付けているのか知りたい</li></ul><p>今回の記事では、名前の付け方について解説します。<br />自作小説のキャラクターに名前を付ける際の、参考になれば嬉しいです。</p>",
    "created": 1647140400,
    "writer": "hano",
    "tags": [
      "書き方",
      "初心者向け"
    ],
    "related": [
      "20220314",
      "20220315",
      "20220316"
    ],
    "slug": "20220313"
  }
]